CHANGES.rst
LICENSE
MANIFEST.in
README.rst
requirements.txt
setup.py
oseti/__init__.py
oseti/oseti.py
oseti/dic/pn_noun.json
oseti/dic/pn_wago.json
osetifix.egg-info/PKG-INFO
osetifix.egg-info/SOURCES.txt
osetifix.egg-info/dependency_links.txt
osetifix.egg-info/requires.txt
osetifix.egg-info/top_level.txt