Metadata-Version: 1.1
Name: osetifix
Version: 0.1.1
Summary: Dictionary based Sentiment Analysis for Japanese
Home-page: https://github.com/ikegami-yukino/oseti
Author: Yukino Ikegami
Author-email: yknikgm@gmail.com
License: MIT License
Keywords: sentiment analysis
Platform: POSIX
Platform: Windows
Platform: Unix
Platform: MacOS
Classifier: Development Status :: 3 - Alpha
Classifier: Intended Audience :: Developers
Classifier: Intended Audience :: Information Technology
Classifier: License :: OSI Approved :: MIT License
Classifier: Natural Language :: Japanese
Classifier: Programming Language :: Python :: 3.4
Classifier: Programming Language :: Python :: 3.5
Classifier: Programming Language :: Python :: 3.6
Classifier: Programming Language :: Python :: 3.7
Classifier: Programming Language :: Python :: 3.8
Classifier: Topic :: Text Processing :: Linguistic
